is_odd_ai/__init__.py
is_odd_ai/is_odd.py
is_odd_ai-0.0.2.post1.dist-info/LICENSE
is_odd_ai-0.0.2.post1.dist-info/METADATA
is_odd_ai-0.0.2.post1.dist-info/WHEEL
is_odd_ai-0.0.2.post1.dist-info/top_level.txt
is_odd_ai-0.0.2.post1.dist-info/RECORD
