Metadata-Version: 2.1
Name: is-odd-ai
Version: 0.0.2.post1
Summary: Check if a number is odd or even using AI
Author: recreationx
License: MIT
Project-URL: Repository, https://github.com/recreationx/is-odd-ai
Project-URL: Issues, https://github.com/recreationx/is-odd-ai/issues
Keywords: odd,even,is odd,is even,is odd ai,is even ai,ai
Requires-Python: >=3.8
License-File: LICENSE
Requires-Dist: requests>=2.32
